odoo/addons/account_statement_import/README.rst
odoo/addons/account_statement_import/__init__.py
odoo/addons/account_statement_import/__manifest__.py
odoo/addons/account_statement_import/demo/partner_bank.xml
odoo/addons/account_statement_import/i18n/account_statement_import.pot
odoo/addons/account_statement_import/i18n/af.po
odoo/addons/account_statement_import/i18n/am.po
odoo/addons/account_statement_import/i18n/ar.po
odoo/addons/account_statement_import/i18n/az.po
odoo/addons/account_statement_import/i18n/bg.po
odoo/addons/account_statement_import/i18n/bs.po
odoo/addons/account_statement_import/i18n/ca.po
odoo/addons/account_statement_import/i18n/cs.po
odoo/addons/account_statement_import/i18n/da.po
odoo/addons/account_statement_import/i18n/de.po
odoo/addons/account_statement_import/i18n/el.po
odoo/addons/account_statement_import/i18n/en_AU.po
odoo/addons/account_statement_import/i18n/en_GB.po
odoo/addons/account_statement_import/i18n/es.po
odoo/addons/account_statement_import/i18n/es_AR.po
odoo/addons/account_statement_import/i18n/es_BO.po
odoo/addons/account_statement_import/i18n/es_CL.po
odoo/addons/account_statement_import/i18n/es_CO.po
odoo/addons/account_statement_import/i18n/es_CR.po
odoo/addons/account_statement_import/i18n/es_DO.po
odoo/addons/account_statement_import/i18n/es_EC.po
odoo/addons/account_statement_import/i18n/es_PE.po
odoo/addons/account_statement_import/i18n/es_PY.po
odoo/addons/account_statement_import/i18n/es_VE.po
odoo/addons/account_statement_import/i18n/et.po
odoo/addons/account_statement_import/i18n/eu.po
odoo/addons/account_statement_import/i18n/fa.po
odoo/addons/account_statement_import/i18n/fi.po
odoo/addons/account_statement_import/i18n/fo.po
odoo/addons/account_statement_import/i18n/fr.po
odoo/addons/account_statement_import/i18n/fr_BE.po
odoo/addons/account_statement_import/i18n/fr_CA.po
odoo/addons/account_statement_import/i18n/fr_FR.po
odoo/addons/account_statement_import/i18n/gl.po
odoo14_addon_account_statement_import-14.0.3.3.3.dist-info/METADATA
odoo14_addon_account_statement_import-14.0.3.3.3.dist-info/WHEEL
odoo14_addon_account_statement_import-14.0.3.3.3.dist-info/top_level.txt
odoo14_addon_account_statement_import-14.0.3.3.3.dist-info/RECORD
