Metadata-Version: 2.1
Name: odoo14-addon-account-statement-import
Version: 14.0.3.3.3
Summary: Import Statement Files
Home-page: https://github.com/OCA/bank-statement-import
Author: Odoo SA, Akretion, Odoo Community Association (OCA)
Author-email: support@odoo-community.org
License: LGPL-3
Platform: UNKNOWN
Classifier: Programming Language :: Python
Classifier: Framework :: Odoo
Classifier: Framework :: Odoo :: 14.0
Classifier: License :: OSI Approved :: GNU Lesser General Public License v3 (LGPLv3)
Classifier: Development Status :: 6 - Mature
Requires-Python: >=3.6
Requires-Dist: odoo14-addon-account-statement-import-base
Requires-Dist: odoo <14.1dev,>=14.0a
